[{"color": [15, 229, 193], "title": "Aberdeen North"}, {"color": [195, 69, 233], "title": "Aberdeen South"}, {"color": [41, 107, 238], "title": "Aldershot"}, {"color": [237, 138, 123], "title": "Aldridge-Brownhills"}, {"color": [106, 205, 180], "title": "Alton and Sherborne"}, {"color": [190, 215, 121], "title": "Altrincham"}, {"color": [46, 172, 226], "title": "Ards and Mid Down"}, {"color": [66, 204, 181], "title": "Argyll, Bute, and Trossachs"}, {"color": [72, 209, 125], "title": "Arundel and Midhurst"}, {"color": [234, 56, 127], "title": "Ascot and Windsor"}, {"color": [93, 162, 219], "title": "Ashfield"}, {"color": [220, 162, 86], "title": "Ashford"}, {"color": [106, 180, 222], "title": "Ashton-under-Lyme"}, {"color": [172, 132, 236], "title": "Aylesbury"}, {"color": [240, 144, 230], "title": "Ayr and Carrick"}, {"color": [236, 228, 120], "title": "Ayrshire North and Arran"}, {"color": [171, 219, 87], "title": "Balham and Southfields"}, {"color": [236, 147, 99], "title": "Banbury and Chipping Norton"}, {"color": [40, 69, 229], "title": "Banff and Buchan"}, {"color": [69, 160, 239], "title": "Barking, Beckton, and Silvertown"}, {"color": [206, 68, 188], "title": "Barnsley East"}, {"color": [230, 56, 218], "title": "Barnsley West"}, {"color": [223, 128, 220], "title": "Barrow and Furness"}, {"color": [73, 229, 114], "title": "Basildon, Wickford, and Pitsea"}, {"color": [177, 222, 126], "title": "Basingstoke"}, {"color": [184, 98, 224], "title": "Bassetlaw"}, {"color": [230, 138, 212], "title": "Bath"}, {"color": [126, 14, 230], "title": "Batley and Cleckheaton\n"}, {"color": [107, 164, 229], "title": "Battersea"}, {"color": [167, 226, 133], "title": "Beaconsfield"}, {"color": [236, 232, 115], "title": "Beckenham"}, {"color": [227, 67, 211], "title": "Becontree"}, {"color": [154, 115, 209], "title": "Bedford"}, {"color": [206, 111, 179], "title": "Belfast Central"}, {"color": [145, 236, 47], "title": "Belfast North and Bangor"}, {"color": [20, 200, 47], "title": "Belfast South"}, {"color": [59, 207, 96], "title": "Belfast West"}, {"color": [97, 157, 221], "title": "Bermondsey"}, {"color": [231, 131, 43], "title": "Berwick and Ashington"}, {"color": [159, 127, 223], "title": "Berwickshire, Selkirk, and Tweeddale"}, {"color": [30, 58, 217], "title": "Bethnal Green and Bow"}, {"color": [127, 28, 208], "title": "Beverley and Pocklington"}, {"color": [228, 55, 25], "title": "Bexhill, Battle, and Polegate"}, {"color": [240, 81, 190], "title": "Bexleyheath"}, {"color": [54, 63, 233], "title": "Bicester and Thame"}, {"color": [182, 138, 230], "title": "Biggleswade and Sandy"}, {"color": [131, 101, 231], "title": "Billericay and Great Baddow"}, {"color": [163, 135, 222], "title": "Birkenhead"}, {"color": [208, 117, 135], "title": "Birmingham Edgbaston"}, {"color": [207, 88, 108], "title": "Birmingham Erdington"}, {"color": [236, 169, 62], "title": "Birmingham Hall Green"}, {"color": [230, 118, 27], "title": "Birmingham King's Norton"}, {"color": [125, 211, 85], "title": "Birmingham Ladywood"}, {"color": [15, 231, 15], "title": "Birmingham Northfield"}, {"color": [240, 49, 62], "title": "Birmingham Perry Barr"}, {"color": [222, 111, 37], "title": "Birmingham Saltley"}, {"color": [210, 200, 127], "title": "Birmingham Sparkbrook"}, {"color": [212, 120, 144], "title": "Birmingham Yardley"}, {"color": [36, 33, 210], "title": "Blaby and Lutterworth"}, {"color": [239, 76, 119], "title": "Blackburn"}, {"color": [70, 229, 110], "title": "Blackdown Hills and Cullompton"}, {"color": [240, 128, 231], "title": "Blackpool"}, {"color": [235, 28, 187], "title": "Blaenau Gwent and Rhymney"}, {"color": [22, 101, 218], "title": "Blairgowrie, Skye, and Wester Ross"}, {"color": [129, 112, 223], "title": "Blaydon"}, {"color": [103, 76, 235], "title": "Bletchley and Buckingham"}, {"color": [239, 225, 75], "title": "Bloxwich and Wolverhampton North East"}, {"color": [221, 16, 23], "title": "Blyth and Cramlington"}, {"color": [109, 166, 202], "title": "Bognor Regis and Littlehampton"}, {"color": [175, 204, 89], "title": "Bolsover"}, {"color": [223, 140, 238], "title": "Bolton North East"}, {"color": [45, 128, 200], "title": "Bolton South East"}, {"color": [90, 202, 116], "title": "Bolton West and Whelley"}, {"color": [183, 37, 212], "title": "Bootle"}, {"color": [32, 46, 208], "title": "Boston and Skegness"}, {"color": [191, 230, 137], "title": "Bournemouth East"}, {"color": [132, 138, 223], "title": "Bournemouth West"}, {"color": [57, 168, 212], "title": "Bracknell"}, {"color": [52, 75, 224], "title": "Bradford North"}, {"color": [67, 202, 114], "title": "Bradford South East"}, {"color": [102, 140, 221], "title": "Bradford South West"}, {"color": [214, 43, 128], "title": "Braintree"}, {"color": [147, 218, 103], "title": "Breckland"}, {"color": [227, 133, 25], "title": "Brent Central"}, {"color": [46, 183, 217], "title": "Brent North"}, {"color": [15, 93, 239], "title": "Brentford and Isleworth"}, {"color": [121, 162, 220], "title": "Brentwood and Ongar"}, {"color": [97, 200, 113], "title": "Bridgend"}, {"color": [179, 51, 211], "title": "Bridgwater and West Somerset"}, {"color": [71, 141, 211], "title": "Brighton Kemptown and Newhaven"}, {"color": [240, 119, 63], "title": "Brighton Pavilion"}, {"color": [202, 80, 131], "title": "Bristol Central"}, {"color": [130, 207, 238], "title": "Bristol North East"}, {"color": [235, 79, 149], "title": "Bristol North West"}, {"color": [182, 217, 54], "title": "Bristol South East"}, {"color": [113, 188, 216], "title": "Bristol South West"}, {"color": [227, 16, 181], "title": "Brixton"}, {"color": [114, 211, 22], "title": "Broadland"}, {"color": [155, 206, 66], "title": "Bromley and Chislehurst"}, {"color": [223, 108, 131], "title": "Bromsgrove"}, {"color": [159, 210, 114], "title": "Broughton and Eccles"}, {"color": [59, 236, 233], "title": "Broxbourne"}, {"color": [28, 215, 118], "title": "Broxtowe"}, {"color": [215, 47, 24], "title": "Burgess Hill and Storrington"}, {"color": [44, 233, 164], "title": "Burnley East and Pendle"}, {"color": [207, 93, 44], "title": "Burnley West and Hyndburn"}, {"color": [176, 213, 128], "title": "Burton and Uttoxeter"}, {"color": [215, 240, 92], "title": "Bury North"}, {"color": [216, 110, 128], "title": "Bury South"}, {"color": [82, 221, 129], "title": "Bury St Edmunds"}, {"color": [207, 191, 18], "title": "Caerphilly"}, {"color": [200, 100, 195], "title": "Caithness, Sutherland, and Easter Ross"}, {"color": [13, 218, 139], "title": "Calder Valley"}, {"color": [21, 195, 214], "title": "Camberwell and Peckham"}, {"color": [229, 39, 166], "title": "Camborne and Redruth"}, {"color": [86, 215, 57], "title": "Cambridge"}, {"color": [175, 96, 231], "title": "Cannock and Burntwood"}, {"color": [198, 203, 122], "title": "Canterbury"}, {"color": [223, 201, 88], "title": "Cardiff East"}, {"color": [234, 76, 202], "title": "Cardiff North"}, {"color": [129, 37, 204], "title": "Cardiff South and Penarth"}, {"color": [155, 86, 239], "title": "Cardiff West"}, {"color": [221, 72, 39], "title": "Carlisle"}, {"color": [225, 158, 65], "title": "Carmarthen"}, {"color": [103, 47, 224], "title": "Carryduff and South Down"}, {"color": [216, 75, 238], "title": "Carshalton and Wallington"}, {"color": [226, 101, 205], "title": "Castle Point"}, {"color": [89, 223, 183], "title": "Central Devon"}, {"color": [57, 232, 235], "title": "Chadderton and Failsworth"}, {"color": [102, 131, 205], "title": "Cheadle"}, {"color": [110, 228, 189], "title": "Chelmsford"}, {"color": [200, 123, 56], "title": "Chelsea and Notting Hill"}, {"color": [103, 128, 216], "title": "Cheltenham"}, {"color": [93, 105, 236], "title": "Chesham and Amersham"}, {"color": [133, 225, 214], "title": "Chesterfield"}, {"color": [207, 186, 68], "title": "Chichester"}, {"color": [94, 118, 237], "title": "Chiltern and the Riseboroughs"}, {"color": [69, 203, 141], "title": "Chingford and Woodford"}, {"color": [226, 56, 115], "title": "Chippenham"}, {"color": [33, 21, 201], "title": "Chipping Barnet"}, {"color": [138, 36, 207], "title": "Chorley"}, {"color": [209, 103, 236], "title": "Christchurch"}, {"color": [29, 48, 223], "title": "Cities of London and Westminster"}, {"color": [220, 223, 68], "title": "City of Chester"}, {"color": [239, 139, 147], "title": "City of Durham"}, {"color": [102, 234, 61], "title": "Clackmannanshire and West Fife"}, {"color": [57, 67, 216], "title": "Clacton"}, {"color": [93, 202, 53], "title": "Clapham and Stockwell"}, {"color": [161, 91, 214], "title": "Clydesdale and Hamilton"}, {"color": [234, 171, 103], "title": "Coatbridge, Airdrie, and Chryston"}, {"color": [25, 217, 19], "title": "Colchester"}, {"color": [229, 100, 60], "title": "Coleraine and Dungiven"}, {"color": [107, 222, 78], "title": "Colne Valley"}, {"color": [222, 126, 225], "title": "Colwyn"}, {"color": [209, 152, 29], "title": "Congleton and Wilmslow"}, {"color": [236, 183, 122], "title": "Consett and Bishop Auckland"}, {"color": [135, 235, 207], "title": "Corby"}, {"color": [145, 235, 65], "title": "Coventry North East"}, {"color": [191, 97, 222], "title": "Coventry North West"}, {"color": [112, 225, 170], "title": "Coventry South"}, {"color": [216, 216, 116], "title": "Craigavon"}, {"color": [158, 215, 24], "title": "Cranbrook and Stratford"}, {"color": [203, 238, 126], "title": "Crawley"}, {"color": [93, 77, 212], "title": "Crewe and Nantwich"}, {"color": [209, 109, 33], "title": "Croydon Central"}, {"color": [201, 91, 199], "title": "Croydon North and Streatham"}, {"color": [203, 68, 66], "title": "Croydon South"}, {"color": [220, 239, 137], "title": "Croydon West"}, {"color": [140, 127, 225], "title": "Dagenham and Rainham"}, {"color": [69, 233, 143], "title": "Darlington"}, {"color": [221, 231, 130], "title": "Dartford"}, {"color": [168, 200, 104], "title": "Daventry"}, {"color": [218, 61, 63], "title": "Denton, Stalybridge, and Hyde"}, {"color": [53, 216, 72], "title": "Derby East"}, {"color": [238, 200, 124], "title": "Derby North West and Belper"}, {"color": [230, 39, 150], "title": "Derby South West"}, {"color": [118, 84, 203], "title": "Derbyshire Dales"}, {"color": [232, 102, 171], "title": "Dewsbury"}, {"color": [73, 211, 165], "title": "Didcot and Wantage"}, {"color": [227, 216, 15], "title": "Don Valley"}, {"color": [229, 41, 207], "title": "Doncaster Central"}, {"color": [207, 215, 48], "title": "Doncaster North"}, {"color": [55, 222, 202], "title": "Dorking and Reigate"}, {"color": [205, 161, 85], "title": "Dover and Deal"}, {"color": [141, 98, 214], "title": "Dromore and Armagh"}, {"color": [217, 19, 111], "title": "Dudley North"}, {"color": [89, 237, 171], "title": "Dudley South"}, {"color": [235, 108, 231], "title": "Dulwich and Sydenham"}, {"color": [152, 107, 203], "title": "Dumfries and Hawick"}, {"color": [67, 203, 234], "title": "Dundee Central"}, {"color": [212, 162, 69], "title": "Dundee East and Arbroath"}, {"color": [152, 222, 61], "title": "Dunfermline and Cowdenbeath"}, {"color": [170, 201, 47], "title": "Dursley, Thornbury, and Yate"}, {"color": [39, 208, 214], "title": "Dyffryn Ceiriog"}, {"color": [190, 239, 29], "title": "Ealing Central and Acton"}, {"color": [226, 62, 196], "title": "Ealing Hanwell"}, {"color": [35, 233, 226], "title": "Ealing Northolt"}, {"color": [90, 229, 35], "title": "Ealing Southall and Yeading"}, {"color": [80, 234, 19], "title": "Easington"}, {"color": [200, 226, 96], "title": "East Antrim"}, {"color": [90, 183, 212], "title": "East Cambridgeshire"}, {"color": [232, 183, 60], "title": "East Derbyshire"}, {"color": [102, 64, 225], "title": "East Devon"}, {"color": [84, 167, 222], "title": "East Dunbartonshire"}, {"color": [96, 232, 205], "title": "East Ham"}, {"color": [74, 129, 237], "title": "East Hampshire"}, {"color": [76, 210, 53], "title": "East Lothian"}, {"color": [199, 108, 217], "title": "East Renfrewshire and Johnstone"}, {"color": [72, 60, 214], "title": "Eastbourne"}, {"color": [226, 21, 148], "title": "Eastleigh"}, {"color": [221, 133, 229], "title": "Edenbridge and Tunbridge Wells"}, {"color": [217, 182, 100], "title": "Edgware and Stanmore"}, {"color": [31, 217, 62], "title": "Edinburgh Central"}, {"color": [138, 215, 231], "title": "Edinburgh North and Leith"}, {"color": [220, 53, 56], "title": "Edinburgh Pentland"}, {"color": [96, 239, 165], "title": "Edinburgh South"}, {"color": [59, 140, 202], "title": "Edinburgh West"}, {"color": [29, 126, 224], "title": "Edmonton"}, {"color": [216, 170, 33], "title": "Ellesmere Port and Neston"}, {"color": [111, 221, 199], "title": "Eltham and Longlands"}, {"color": [167, 40, 236], "title": "Enfield North East"}, {"color": [74, 218, 139], "title": "Enfield West"}, {"color": [234, 219, 137], "title": "Epping and Waltham"}, {"color": [216, 240, 81], "title": "Epsom, Ewell, and Banstead"}, {"color": [80, 132, 229], "title": "Erewash"}, {"color": [228, 179, 133], "title": "Erith and Heath"}, {"color": [54, 158, 222], "title": "Esher and Walton"}, {"color": [211, 37, 21], "title": "Exeter"}, {"color": [140, 130, 232], "title": "Fairlop"}, {"color": [218, 79, 169], "title": "Falkirk"}, {"color": [161, 233, 61], "title": "Fareham and Purbrook"}, {"color": [228, 139, 179], "title": "Farnham"}, {"color": [233, 175, 128], "title": "Feltham and Hampton"}, {"color": [205, 79, 115], "title": "Fenland"}, {"color": [85, 204, 25], "title": "Filton and Bradley Stoke"}, {"color": [48, 92, 237], "title": "Finchley and Golders Green"}, {"color": [65, 236, 133], "title": "Findon, Shoreham, and Steyning"}, {"color": [117, 205, 210], "title": "Fleetwood and Blackpool North"}, {"color": [204, 121, 136], "title": "Flintshire"}, {"color": [226, 213, 98], "title": "Folkestone and Hythe"}, {"color": [216, 71, 226], "title": "Forest of Dean"}, {"color": [83, 204, 67], "title": "Forfar and Strathmore"}, {"color": [105, 217, 77], "title": "Foyle"}, {"color": [185, 88, 224], "title": "Fulham"}, {"color": [119, 215, 84], "title": "Fylde"}, {"color": [226, 197, 81], "title": "Gainsborough and Broughton"}, {"color": [119, 220, 97], "title": "Galloway and Cumnock"}, {"color": [163, 135, 228], "title": "Gateshead"}, {"color": [190, 206, 44], "title": "Gedling"}, {"color": [205, 81, 147], "title": "Gillingham and Chatham"}, {"color": [74, 173, 239], "title": "Glasgow Central and Renfrew"}, {"color": [24, 211, 105], "title": "Glasgow East"}, {"color": [186, 112, 210], "title": "Glasgow North"}, {"color": [155, 88, 236], "title": "Glasgow North East"}, {"color": [136, 224, 238], "title": "Glasgow North West"}, {"color": [23, 73, 210], "title": "Glasgow South"}, {"color": [118, 97, 207], "title": "Gloucester"}, {"color": [90, 235, 221], "title": "Godalming and Cobham"}, {"color": [49, 154, 203], "title": "Goole and Howden"}, {"color": [63, 219, 110], "title": "Gosport and Stubbington"}, {"color": [96, 112, 237], "title": "Gower and Swansea West"}, {"color": [14, 185, 204], "title": "Gravesham"}, {"color": [114, 90, 220], "title": "Great Yarmouth"}, {"color": [158, 231, 40], "title": "Greenwich"}, {"color": [210, 58, 69], "title": "Grimsby and Cleethorpes"}, {"color": [238, 117, 179], "title": "Guildford"}, {"color": [78, 218, 18], "title": "Hackney North and Homerton"}, {"color": [218, 109, 151], "title": "Hackney South and Shoreditch"}, {"color": [50, 176, 230], "title": "Hailsham and Crowborough"}, {"color": [184, 121, 215], "title": "Halesowen and Stourbridge"}, {"color": [183, 54, 212], "title": "Halifax"}, {"color": [199, 207, 113], "title": "Hallam and Stocksbridge"}, {"color": [94, 232, 133], "title": "Hammersmith and Harlesden"}, {"color": [205, 207, 58], "title": "Hampstead and Highgate"}, {"color": [215, 196, 99], "title": "Harborough and Oadby"}, {"color": [130, 167, 231], "title": "Haringay and Stoke Newington"}, {"color": [48, 121, 238], "title": "Harlech, Newtown, and Ystwyth"}, {"color": [115, 157, 208], "title": "Harlow"}, {"color": [129, 79, 208], "title": "Harrogate and Knaresborough"}, {"color": [229, 25, 124], "title": "Harrow East and Weald"}, {"color": [135, 84, 211], "title": "Harrow West and Pinner"}, {"color": [78, 215, 208], "title": "Hart"}, {"color": [170, 207, 75], "title": "Hartlepool"}, {"color": [209, 56, 99], "title": "Harwich and North Essex"}, {"color": [54, 164, 200], "title": "Hastings and Rye"}, {"color": [231, 66, 157], "title": "Havant"}, {"color": [50, 81, 233], "title": "Hayes, Harlington, and Bedfont"}, {"color": [181, 210, 103], "title": "Hazel Grove"}, {"color": [52, 87, 201], "title": "Hemel Hempstead"}, {"color": [112, 165, 214], "title": "Hemsworth and Pontefract"}, {"color": [187, 136, 238], "title": "Hendon"}, {"color": [201, 217, 23], "title": "Henley"}, {"color": [19, 80, 225], "title": "Hereford and Ross"}, {"color": [173, 107, 214], "title": "Herefordshire North and West"}, {"color": [132, 228, 215], "title": "Hertsmere"}, {"color": [135, 50, 209], "title": "Heston and Hounslow"}, {"color": [194, 217, 120], "title": "Hexham and Morpeth"}, {"color": [74, 214, 27], "title": "Heywood and Middleton"}, {"color": [25, 232, 211], "title": "High Peak"}, {"color": [221, 66, 221], "title": "Hinckley and Bosworth"}, {"color": [114, 106, 206], "title": "Hitchin"}, {"color": [216, 221, 69], "title": "Holbech, Sutton, and Spalding"}, {"color": [225, 113, 57], "title": "Holborn and Gospel Oak"}, {"color": [204, 83, 67], "title": "Holderness and Bridlington"}, {"color": [151, 101, 216], "title": "Hornchurch and Upminster"}, {"color": [165, 34, 212], "title": "Hornsey and New Southgate"}, {"color": [118, 227, 150], "title": "Horsham"}, {"color": [123, 86, 217], "title": "Houghton and Sunderland South"}, {"color": [71, 204, 82], "title": "Hove"}, {"color": [141, 206, 121], "title": "Huddersfield"}, {"color": [211, 82, 228], "title": "Huyton and Halewood"}, {"color": [225, 84, 84], "title": "Ilford"}, {"color": [17, 213, 23], "title": "Immingham and the Wolds"}, {"color": [109, 60, 200], "title": "Inverclyde and Crosslee"}, {"color": [204, 62, 46], "title": "Inverness, Nairn, Badenoch, and Strathspey"}, {"color": [227, 130, 123], "title": "Ipswich"}, {"color": [234, 71, 65], "title": "Isle of Wight East"}, {"color": [198, 220, 132], "title": "Isle of Wight West"}, {"color": [230, 64, 119], "title": "Islington North"}, {"color": [74, 202, 155], "title": "Islington South and Finsbury"}, {"color": [95, 159, 237], "title": "Jarrow and Washington"}, {"color": [117, 200, 185], "title": "Keighley"}, {"color": [230, 137, 216], "title": "Kendal and Lonsdale"}, {"color": [201, 68, 112], "title": "Kenilworth and Southam"}, {"color": [233, 104, 79], "title": "Kensington, Kensal, and Queen's Park"}, {"color": [214, 211, 126], "title": "Kettering"}, {"color": [208, 75, 88], "title": "Kilmarnock and Irvine"}, {"color": [225, 109, 160], "title": "Kilsyth, Cumbernauld, and Shotts"}, {"color": [76, 224, 123], "title": "King's Lynn and Downham"}, {"color": [57, 240, 185], "title": "Kingston and Surbiton"}, {"color": [102, 214, 85], "title": "Kingston upon Hull East"}, {"color": [91, 88, 237], "title": "Kingston upon Hull North"}, {"color": [221, 58, 178], "title": "Kingston upon Hull West and Cottingham"}, {"color": [34, 209, 72], "title": "Kingswood"}, {"color": [48, 207, 53], "title": "Kirkcaldy"}, {"color": [106, 229, 198], "title": "Lambeth and Southwark"}, {"color": [233, 160, 34], "title": "Lampeter, Cardigan, and St. Clears"}, {"color": [222, 84, 114], "title": "Launceston and Saltash"}, {"color": [71, 222, 83], "title": "Leeds Central"}, {"color": [235, 31, 120], "title": "Leeds East"}, {"color": [103, 60, 234], "title": "Leeds North"}, {"color": [28, 80, 203], "title": "Leeds South"}, {"color": [132, 217, 223], "title": "Leeds West"}, {"color": [218, 31, 21], "title": "Leicester Central"}, {"color": [50, 97, 239], "title": "Leicester East"}, {"color": [56, 130, 209], "title": "Leicester West"}, {"color": [14, 214, 204], "title": "Leigh"}, {"color": [200, 49, 147], "title": "Lewes and Uckfield"}, {"color": [210, 106, 191], "title": "Lewisham North"}, {"color": [76, 21, 226], "title": "Lewisham South and Horn Park"}, {"color": [95, 153, 229], "title": "Leyton and Wanstead"}, {"color": [234, 158, 119], "title": "Lincoln and North Hykeham"}, {"color": [93, 230, 166], "title": "Linlithgow and East Falkirk"}, {"color": [94, 223, 39], "title": "Lisburn and Lagan"}, {"color": [215, 156, 79], "title": "Liverpool Garston"}, {"color": [23, 233, 51], "title": "Liverpool Riverside"}, {"color": [103, 236, 82], "title": "Liverpool Walton"}, {"color": [85, 90, 224], "title": "Liverpool Wavertree"}, {"color": [228, 163, 65], "title": "Liverpool West Derby"}, {"color": [60, 229, 170], "title": "Livingston"}, {"color": [12, 160, 205], "title": "Llanelli and Gorseinon"}, {"color": [213, 239, 17], "title": "Llanelwy and the Vale of Clwyd"}, {"color": [130, 180, 216], "title": "Loughborough"}, {"color": [199, 21, 202], "title": "Lowestoft"}, {"color": [16, 230, 137], "title": "Ludlow"}, {"color": [217, 195, 123], "title": "Lune, Wyre, and Preston North"}, {"color": [72, 230, 106], "title": "Luton North"}, {"color": [222, 123, 153], "title": "Luton South"}, {"color": [127, 230, 31], "title": "Luton West and South Bedfordshire"}, {"color": [148, 57, 212], "title": "Lydd and the Weald"}, {"color": [40, 224, 116], "title": "Macclesfield"}, {"color": [216, 100, 229], "title": "Maidenhead"}, {"color": [224, 89, 201], "title": "Maidstone"}, {"color": [87, 175, 219], "title": "Makerfield"}, {"color": [146, 205, 73], "title": "Malden and Barnes"}, {"color": [217, 158, 85], "title": "Maldon"}, {"color": [240, 72, 34], "title": "Malvern and Pershore"}, {"color": [231, 150, 123], "title": "Manchester Blackley"}, {"color": [55, 85, 216], "title": "Manchester Central"}, {"color": [225, 50, 82], "title": "Manchester Didsbury"}, {"color": [140, 233, 186], "title": "Manchester Gorton"}, {"color": [124, 163, 220], "title": "Manchester Withington"}, {"color": [200, 95, 153], "title": "Mansfield"}, {"color": [235, 155, 75], "title": "Melksham and Devizes"}, {"color": [89, 230, 14], "title": "Melton and Grantham"}, {"color": [102, 240, 145], "title": "Menai"}, {"color": [201, 13, 13], "title": "Meriden"}, {"color": [103, 23, 215], "title": "Merthyr Tydfil and Ystrad Mynach"}, {"color": [157, 216, 84], "title": "Mid Antrim"}, {"color": [70, 229, 26], "title": "Mid Bedfordshire"}, {"color": [122, 207, 230], "title": "Mid Cambridgeshire"}, {"color": [83, 50, 201], "title": "Mid Norfolk"}, {"color": [87, 238, 147], "title": "Mid Northamptonshire"}, {"color": [143, 218, 239], "title": "Mid Somerset"}, {"color": [108, 223, 162], "title": "Mid Suffolk"}, {"color": [229, 95, 129], "title": "Mid Sussex"}, {"color": [222, 14, 24], "title": "Mid Ulster"}, {"color": [236, 179, 23], "title": "Middlesbrough"}, {"color": [201, 235, 134], "title": "Middlesbrough West and Yarm"}, {"color": [114, 16, 226], "title": "Midlothian and Colinton"}, {"color": [34, 38, 225], "title": "Milnrow, Springhead, and Saddleworth"}, {"color": [179, 101, 202], "title": "Milton Keynes Central"}, {"color": [96, 212, 185], "title": "Milton Keynes North"}, {"color": [181, 98, 236], "title": "Mitcham and Tooting"}, {"color": [189, 92, 200], "title": "Monmouth and Brecon"}, {"color": [18, 235, 76], "title": "Moray"}, {"color": [147, 143, 239], "title": "Morecambe and Lancaster"}, {"color": [222, 182, 23], "title": "Morley and Outwood"}, {"color": [61, 90, 207], "title": "Motherwell and Wishaw"}, {"color": [49, 218, 145], "title": "Na h-Eileanan Siar"}, {"color": [236, 225, 123], "title": "Neath Port Talbot"}, {"color": [127, 192, 239], "title": "New Forest East and Romsey"}, {"color": [99, 230, 210], "title": "New Forest West"}, {"color": [215, 18, 130], "title": "Newark and Southwell"}, {"color": [127, 217, 235], "title": "Newbury and Thatcham"}, {"color": [223, 52, 226], "title": "Newcastle under Lyme"}, {"color": [206, 39, 58], "title": "Newcastle upon Tyne Central"}, {"color": [169, 60, 209], "title": "Newcastle Upon Tyne North"}, {"color": [206, 181, 117], "title": "Newcastle upon Tyne West"}, {"color": [75, 228, 233], "title": "Newport Central"}, {"color": [204, 238, 142], "title": "Newport East and Chestow"}, {"color": [200, 84, 192], "title": "Newquay and Bodmin"}, {"color": [101, 239, 124], "title": "Newry and Mourne"}, {"color": [66, 209, 138], "title": "Newton Abbott and Teignmouth"}, {"color": [206, 127, 95], "title": "Normanton and Castleford"}, {"color": [206, 79, 33], "title": "North Antrim and Ballymena"}, {"color": [216, 28, 213], "title": "North Devon"}, {"color": [88, 200, 56], "title": "North Durham"}, {"color": [74, 65, 235], "title": "North East Dorset"}, {"color": [58, 49, 220], "title": "North East Fife and Glenrothes"}, {"color": [234, 88, 110], "title": "North East Somerset"}, {"color": [58, 217, 231], "title": "North Norfolk"}, {"color": [210, 228, 72], "title": "North Somerset"}, {"color": [238, 91, 150], "title": "North Warwickshire"}, {"color": [167, 28, 226], "title": "North West Bedfordshire"}, {"color": [104, 233, 149], "title": "North West Leicestershire"}, {"color": [233, 144, 134], "title": "Northampton North"}, {"color": [100, 175, 212], "title": "Northampton South"}, {"color": [227, 69, 108], "title": "Norwich North"}, {"color": [50, 230, 116], "title": "Norwich South and Wymondham"}, {"color": [132, 209, 222], "title": "Nottingham East"}, {"color": [223, 79, 31], "title": "Nottingham South and West Bridgford"}, {"color": [127, 62, 240], "title": "Nottingham West"}, {"color": [223, 62, 210], "title": "Nuneaton and Bedworth"}, {"color": [86, 206, 202], "title": "Ogmore, Treorchy, and Glynneath"}, {"color": [200, 157, 38], "title": "Oldham and Royton"}, {"color": [130, 215, 182], "title": "Omagh and Strabane"}, {"color": [239, 67, 90], "title": "Orkney and Shetland"}, {"color": [83, 234, 66], "title": "Orpington"}, {"color": [90, 164, 234], "title": "Owestry and Drayton"}, {"color": [142, 201, 54], "title": "Oxford East"}, {"color": [211, 239, 140], "title": "Oxford West and Abingdon"}, {"color": [85, 69, 230], "title": "Paisley and Erskine"}, {"color": [30, 209, 30], "title": "Pembrokeshire"}, {"color": [236, 218, 102], "title": "Penrith and the Border"}, {"color": [213, 20, 149], "title": "Penzance and St Ives"}, {"color": [216, 105, 26], "title": "Perth and Kinross"}, {"color": [106, 228, 97], "title": "Peterborough Central"}, {"color": [90, 226, 99], "title": "Peterborough East"}, {"color": [193, 16, 202], "title": "Peterborough West and Huntingdon"}, {"color": [52, 238, 46], "title": "Plymouth Moor View"}, {"color": [208, 205, 42], "title": "Plymouth Sutton and Devonport"}, {"color": [214, 29, 51], "title": "Plympton and South Devon"}, {"color": [214, 91, 104], "title": "Pontypridd"}, {"color": [146, 219, 64], "title": "Poole"}, {"color": [69, 181, 201], "title": "Poplar"}, {"color": [228, 119, 79], "title": "Portsmouth North"}, {"color": [137, 215, 73], "title": "Portsmouth South"}, {"color": [232, 130, 220], "title": "Potters Bar and Hertford"}, {"color": [39, 219, 81], "title": "Preston"}, {"color": [36, 226, 19], "title": "Pudsey"}, {"color": [222, 193, 106], "title": "Putney"}, {"color": [211, 150, 58], "title": "Reading East"}, {"color": [219, 15, 59], "title": "Reading West and Tilehurst"}, {"color": [152, 237, 83], "title": "Redcar and Cleveland"}, {"color": [63, 218, 43], "title": "Redditch and Droitwich"}, {"color": [236, 173, 27], "title": "Redhill and Horley"}, {"color": [54, 211, 111], "title": "Rhondda and Cynon"}, {"color": [26, 228, 63], "title": "Ribble Valley and Brierfield"}, {"color": [230, 133, 201], "title": "Richmond and Northallerton"}, {"color": [203, 226, 74], "title": "Richmond and Twickenham"}, {"color": [120, 216, 56], "title": "Rochdale"}, {"color": [96, 238, 238], "title": "Rochester and Strood"}, {"color": [133, 238, 147], "title": "Rochford and Rayleigh"}, {"color": [82, 39, 202], "title": "Romford"}, {"color": [226, 101, 70], "title": "Rossendale and Darwen"}, {"color": [127, 46, 208], "title": "Rother Valley"}, {"color": [48, 219, 46], "title": "Rotherham"}, {"color": [220, 196, 107], "title": "Rothwell and Garforth"}, {"color": [197, 109, 203], "title": "Rugby"}, {"color": [203, 103, 218], "title": "Ruislip and Northwood"}, {"color": [33, 43, 222], "title": "Runnymede and Weybridge"}, {"color": [172, 235, 110], "title": "Rushcliffe"}, {"color": [88, 233, 97], "title": "Rutherglen and Cambuslang"}, {"color": [217, 102, 156], "title": "Rutland and Stamford"}, {"color": [182, 220, 14], "title": "Saffron Walden"}, {"color": [201, 191, 45], "title": "Sale, Stretford, and Urmston"}, {"color": [139, 230, 218], "title": "Salisbury"}, {"color": [119, 210, 208], "title": "Sandbach"}, {"color": [213, 190, 85], "title": "Sandwell West"}, {"color": [195, 210, 94], "title": "Scarborough and Whitby"}, {"color": [71, 240, 102], "title": "Scunthorpe"}, {"color": [135, 186, 224], "title": "Sedgefield and Aycliffe"}, {"color": [71, 191, 207], "title": "Sefton and Kirkby"}, {"color": [72, 116, 237], "title": "Selby"}, {"color": [159, 239, 102], "title": "Sevenoaks"}, {"color": [28, 218, 25], "title": "Sheffield Brightside"}, {"color": [214, 149, 113], "title": "Sheffield Central and Hillsborough"}, {"color": [213, 94, 179], "title": "Sheffield Nether Edge"}, {"color": [214, 158, 105], "title": "Sheffield South East"}, {"color": [127, 36, 206], "title": "Sheppey and Rainham"}, {"color": [66, 209, 80], "title": "Shifnal and the Wrekin"}, {"color": [120, 232, 40], "title": "Shipley"}, {"color": [154, 204, 120], "title": "Shrewsbury"}, {"color": [213, 109, 175], "title": "Sidcup and Crayford"}, {"color": [239, 185, 76], "title": "Sittingbourne and Faversham"}, {"color": [21, 47, 219], "title": "Skipton and Ripon"}, {"color": [221, 37, 154], "title": "Sleaford and the Fens"}, {"color": [90, 33, 222], "title": "Slough North"}, {"color": [97, 229, 123], "title": "Slough South"}, {"color": [165, 234, 128], "title": "Solihull"}, {"color": [13, 36, 212], "title": "Somerton and Frome"}, {"color": [116, 220, 204], "title": "South Aberdeenshire and Kincardine"}, {"color": [107, 55, 203], "title": "South Cambridgeshire"}, {"color": [108, 103, 235], "title": "South Derbyshire"}, {"color": [57, 150, 200], "title": "South East Dorset"}, {"color": [127, 214, 77], "title": "South Norfolk"}, {"color": [220, 35, 103], "title": "South Ribble"}, {"color": [168, 87, 206], "title": "South Shields"}, {"color": [204, 60, 161], "title": "South Staffordshire"}, {"color": [73, 227, 42], "title": "South Ulster"}, {"color": [205, 143, 104], "title": "South West Bedfordshire"}, {"color": [214, 212, 70], "title": "Southampton East and Titchfield"}, {"color": [240, 69, 56], "title": "Southampton Itchen"}, {"color": [91, 235, 166], "title": "Southampton West"}, {"color": [173, 111, 206], "title": "Southend East"}, {"color": [200, 200, 25], "title": "Southend West"}, {"color": [215, 183, 69], "title": "Southport"}, {"color": [206, 102, 110], "title": "Spelthorne"}, {"color": [115, 183, 214], "title": "St Albans"}, {"color": [205, 84, 77], "title": "St Austell and Liskeard"}, {"color": [209, 102, 166], "title": "St Helens North"}, {"color": [232, 78, 39], "title": "St Helens South and Prescot"}, {"color": [212, 92, 58], "title": "St Neots"}, {"color": [82, 232, 66], "title": "Stafford and Hanford"}, {"color": [168, 217, 77], "title": "Staffordshire Moorlands"}, {"color": [206, 51, 56], "title": "Stepney and Limehouse"}, {"color": [147, 83, 215], "title": "Stevenage"}, {"color": [35, 210, 26], "title": "Stirling"}, {"color": [218, 186, 41], "title": "Stockport and Reddish"}, {"color": [122, 222, 59], "title": "Stockton on Tees"}, {"color": [51, 165, 227], "title": "Stoke on Trent North"}, {"color": [219, 105, 160], "title": "Stoke on Trent South"}, {"color": [80, 233, 88], "title": "Stone, Rugeley, and Lichfield"}, {"color": [118, 146, 230], "title": "Stortford and Royston"}, {"color": [86, 205, 167], "title": "Stratford on Avon"}, {"color": [104, 226, 106], "title": "Strathaven and East Kilbride"}, {"color": [12, 212, 169], "title": "Stroud"}, {"color": [58, 212, 179], "title": "Sudbury and Haverhill"}, {"color": [233, 29, 145], "title": "Suffolk Coastal"}, {"color": [14, 165, 203], "title": "Suffolk Heaths"}, {"color": [211, 116, 108], "title": "Sunderland Central"}, {"color": [235, 63, 189], "title": "Surrey Heath and Ash Vale"}, {"color": [223, 237, 32], "title": "Sutton and Cheam"}, {"color": [158, 227, 105], "title": "Sutton and Waddington"}, {"color": [150, 227, 115], "title": "Sutton Coldfield"}, {"color": [234, 73, 124], "title": "Swansea East"}, {"color": [85, 58, 236], "title": "Swindon North"}, {"color": [98, 225, 214], "title": "Swindon South"}, {"color": [180, 92, 231], "title": "Syston and North Leicester"}, {"color": [212, 106, 26], "title": "Tamworth and Fazeley"}, {"color": [30, 240, 121], "title": "Tandridge and Merstham"}, {"color": [80, 237, 145], "title": "Taunton Deane"}, {"color": [182, 119, 200], "title": "Telford"}, {"color": [220, 30, 74], "title": "Tempsford"}, {"color": [210, 100, 57], "title": "Test Valley"}, {"color": [25, 91, 233], "title": "Tewkesbury"}, {"color": [149, 224, 74], "title": "Thanet East"}, {"color": [49, 176, 218], "title": "Thanet West and Herne Bay"}, {"color": [60, 234, 161], "title": "The Cotswolds"}, {"color": [110, 110, 220], "title": "Thirsk and Malton"}, {"color": [42, 16, 210], "title": "Three Rivers"}, {"color": [57, 202, 204], "title": "Thurnham, Burham, and Walderslade"}, {"color": [82, 198, 206], "title": "Thurrock East"}, {"color": [34, 114, 226], "title": "Thurrock West"}, {"color": [15, 52, 217], "title": "Tonbridge and Malling"}, {"color": [229, 121, 161], "title": "Torbay"}, {"color": [68, 220, 228], "title": "Torfaen and Newport North"}, {"color": [200, 79, 121], "title": "Torridge and West Devon"}, {"color": [70, 225, 85], "title": "Totnes"}, {"color": [232, 78, 124], "title": "Tottenham and Wood Green"}, {"color": [180, 94, 229], "title": "Trafford and Salford"}, {"color": [21, 209, 165], "title": "Tring and Harpenden"}, {"color": [45, 185, 203], "title": "Truro and Falmouth"}, {"color": [114, 221, 214], "title": "Tynemouth"}, {"color": [55, 228, 173], "title": "Uxbridge and Hillingdon"}, {"color": [223, 80, 187], "title": "Vale of Glamorgan"}, {"color": [223, 121, 77], "title": "Wakefield"}, {"color": [214, 108, 238], "title": "Wallasey"}, {"color": [182, 230, 105], "title": "Wallsend"}, {"color": [25, 202, 131], "title": "Walsall South"}, {"color": [229, 159, 30], "title": "Walthamstow"}, {"color": [197, 225, 60], "title": "Warley and Smethwick"}, {"color": [150, 38, 236], "title": "Warrington North"}, {"color": [209, 217, 56], "title": "Warrington South East and Knutsford"}, {"color": [73, 38, 213], "title": "Warrington South West and Northwich"}, {"color": [76, 45, 203], "title": "Warwick and Leamington"}, {"color": [75, 75, 206], "title": "Watford"}, {"color": [75, 55, 232], "title": "Wath and Ecclesfield"}, {"color": [203, 135, 96], "title": "Wellingborough"}, {"color": [33, 102, 212], "title": "Wells"}, {"color": [238, 172, 132], "title": "Welwyn Hatfield"}, {"color": [232, 17, 203], "title": "Wembley"}, {"color": [214, 74, 95], "title": "West Aberdeenshire"}, {"color": [208, 140, 95], "title": "West Bromwich"}, {"color": [121, 60, 212], "title": "West Dorset"}, {"color": [204, 103, 102], "title": "West Dunbartonshire and Forth"}, {"color": [60, 240, 165], "title": "West Ham"}, {"color": [209, 187, 20], "title": "West Lancashire"}, {"color": [58, 219, 208], "title": "West Wiltshire"}, {"color": [81, 210, 74], "title": "Westminster North"}, {"color": [210, 84, 179], "title": "Weston-super-Mare"}, {"color": [224, 99, 174], "title": "Weymouth and Dorchester"}, {"color": [228, 163, 59], "title": "Whitley and Woodley"}, {"color": [84, 203, 90], "title": "Widnes and Runcorn"}, {"color": [80, 218, 68], "title": "Wigan"}, {"color": [100, 212, 80], "title": "Wiltshire Downs and Warminster"}, {"color": [220, 116, 170], "title": "Wimbledon and Morden"}, {"color": [209, 47, 237], "title": "Winchester"}, {"color": [93, 200, 128], "title": "Winsford and Mid Cheshire"}, {"color": [200, 73, 212], "title": "Wirral South and West"}, {"color": [70, 30, 215], "title": "Witham"}, {"color": [162, 41, 222], "title": "Witney"}, {"color": [102, 151, 214], "title": "Woking"}, {"color": [84, 204, 156], "title": "Wokingham"}, {"color": [71, 216, 177], "title": "Wolverhampton South"}, {"color": [210, 26, 220], "title": "Wolverhampton West"}, {"color": [59, 237, 186], "title": "Woolwich and Thamesmead"}, {"color": [201, 161, 119], "title": "Worcester"}, {"color": [218, 121, 218], "title": "Workington and Whitehaven"}, {"color": [160, 201, 72], "title": "Worsley and Irlam"}, {"color": [208, 108, 80], "title": "Worthing"}, {"color": [240, 131, 198], "title": "Wrexham and Buckley"}, {"color": [225, 47, 115], "title": "Wychavon"}, {"color": [200, 49, 167], "title": "Wycombe and Marlow"}, {"color": [220, 129, 17], "title": "Wyre Forest"}, {"color": [79, 107, 206], "title": "Yeovil and Chard"}, {"color": [104, 108, 226], "title": "Ynys Mon"}, {"color": [235, 113, 42], "title": "York Central"}, {"color": [137, 213, 225], "title": "York Outer"}, {"color": [159, 56, 200], "title": ""}]